returnn/PKG-INFO
returnn/__init__.py
returnn/__main__.py
returnn/__old_mod_loader__.py
returnn/__setup__.py
returnn/_setup_info_generated.py
returnn/config.py
returnn/forward_iface.py
returnn/learning_rate_control.py
returnn/log.py
returnn/native_op.cpp
returnn/native_op.py
returnn/pretrain.py
returnn/datasets/__init__.py
returnn/datasets/audio.py
returnn/datasets/basic.py
returnn/datasets/bundle_file.py
returnn/datasets/cached.py
returnn/datasets/cached2.py
returnn/datasets/distrib_files.py
returnn/datasets/generating.py
returnn/datasets/hdf.py
returnn/datasets/huggingface.py
returnn/datasets/lm.py
returnn/datasets/map.py
returnn/datasets/meta.py
returnn/datasets/multi_proc.py
returnn/datasets/normalization_data.py
returnn/datasets/numpy_dump.py
returnn/datasets/postprocessing.py
returnn/datasets/raw_wav.py
returnn/datasets/sprint.py
returnn/datasets/stereo.py
returnn/datasets/text_dict.py
returnn/datasets/util/__init__.py
returnn/datasets/util/feature_extraction.py
returnn/datasets/util/strings.py
returnn/datasets/util/vocabulary.py
returnn/engine/__init__.py
returnn/engine/base.py
returnn/engine/batch.py
returnn/extern/__init__.py
returnn/extern/WarpRna/__init__.py
returnn/extern/WarpRna/__main__.py
returnn/extern/WarpRna/warp-rna/.git
returnn/extern/WarpRna/warp-rna/.gitignore
returnn/extern/WarpRna/warp-rna/LICENSE
returnn/extern/WarpRna/warp-rna/README.md
returnn/extern/WarpRna/warp-rna/aligner.gif
returnn/extern/WarpRna/warp-rna/check.png
returnn/extern/WarpRna/warp-rna/core.cu
returnn/extern/WarpRna/warp-rna/core.h
returnn/extern/WarpRna/warp-rna/core_cpu.cpp
returnn/extern/WarpRna/warp-rna/ref_rna.py
returnn/extern/WarpRna/warp-rna/test.cpp
returnn/extern/WarpRna/warp-rna/pytorch_binding/LICENSE
returnn/extern/WarpRna/warp-rna/pytorch_binding/MANIFEST.in
returnn/extern/WarpRna/warp-rna/pytorch_binding/README.md
returnn/extern/WarpRna/warp-rna/pytorch_binding/binding.cpp
returnn/extern/WarpRna/warp-rna/pytorch_binding/core.cu
returnn-1.20260131.122658.dist-info/LICENSE
returnn-1.20260131.122658.dist-info/METADATA
returnn-1.20260131.122658.dist-info/WHEEL
returnn-1.20260131.122658.dist-info/top_level.txt
returnn-1.20260131.122658.dist-info/RECORD
