Metadata-Version: 2.1
Name: returnn
Version: 1.20260131.122658
Summary: The RWTH extensible training framework for universal recurrent neural networks
Home-page: https://github.com/rwth-i6/returnn/
Author: Albert Zeyer
Author-email: albzey@gmail.com
License: RETURNN license
Classifier: Development Status :: 5 - Production/Stable
Classifier: Environment :: Console
Classifier: Environment :: GPU
Classifier: Environment :: GPU :: NVIDIA CUDA
Classifier: Intended Audience :: Developers
Classifier: Intended Audience :: Education
Classifier: Intended Audience :: Science/Research
Classifier: License :: Other/Proprietary License
Classifier: Operating System :: MacOS :: MacOS X
Classifier: Operating System :: Microsoft :: Windows
Classifier: Operating System :: POSIX
Classifier: Operating System :: Unix
Classifier: Programming Language :: Python
Classifier: Programming Language :: Python :: 3
Classifier: Topic :: Scientific/Engineering
Classifier: Topic :: Scientific/Engineering :: Artificial Intelligence
Classifier: Topic :: Software Development :: Libraries :: Python Modules
License-File: LICENSE
Requires-Dist: numpy
